arthur/__init__.py
arthur/_version.py
arthur/arthur.py
arthur/bin/arthurd.py
arthur/bin/arthurw.py
arthur/common.py
arthur/errors.py
arthur/events.py
arthur/jobs.py
arthur/scheduler.py
arthur/server.py
arthur/tasks.py
arthur/utils.py
arthur/worker.py
arthur/writers.py
kingarthur-0.2.5.dist-info/entry_points.txt
kingarthur-0.2.5.dist-info/LICENSE
kingarthur-0.2.5.dist-info/WHEEL
kingarthur-0.2.5.dist-info/METADATA
kingarthur-0.2.5.dist-info/RECORD
