Metadata-Version: 2.1
Name: kingarthur
Version: 0.2.5
Summary: Distributed job queue platform for scheduling Perceval jobs
Home-page: https://chaoss.github.io/grimoirelab/
License: GPL-3.0+
Keywords: development,grimoirelab
Author: GrimoireLab Developers
Requires-Python: >=3.7,<4.0
Classifier: Development Status :: 4 - Beta
Classifier: Intended Audience :: Developers
Classifier: Intended Audience :: Science/Research
Classifier: License :: OSI Approved :: GNU General Public License v3 or later (GPLv3+)
Classifier: Programming Language :: Python :: 3
Classifier: Programming Language :: Python :: 3.7
Classifier: Programming Language :: Python :: 3.8
Classifier: Programming Language :: Python :: 3.9
Classifier: Programming Language :: Python :: 3.10
Classifier: Programming Language :: Python :: 3.11
Classifier: Programming Language :: Python :: 3
Classifier: Topic :: Software Development
Requires-Dist: autocommand (==2.2.1)
Requires-Dist: beautifulsoup4 (==4.11.1)
Requires-Dist: certifi (==2022.9.24)
Requires-Dist: cffi (==1.15.1)
Requires-Dist: charset-normalizer (==2.1.1)
Requires-Dist: cheroot (==8.6.0)
Requires-Dist: cherrypy (==18.8.0)
Requires-Dist: click (==8.1.3)
Requires-Dist: cryptography (==3.4.8)
Requires-Dist: dulwich (==0.20.50)
Requires-Dist: feedparser (==6.0.10)
Requires-Dist: grimoirelab-toolkit (==0.3.2)
Requires-Dist: idna (==3.4)
Requires-Dist: inflect (==6.0.2)
Requires-Dist: jaraco-classes (==3.2.3)
Requires-Dist: jaraco-collections (==3.8.0)
Requires-Dist: jaraco-context (==4.1.2)
Requires-Dist: jaraco-functools (==3.5.2)
Requires-Dist: jaraco-text (==3.10.0)
Requires-Dist: more-itertools (==9.0.0)
Requires-Dist: perceval (==0.21.1)
Requires-Dist: portend (==3.1.0)
Requires-Dist: pycparser (==2.21)
Requires-Dist: pydantic (==1.10.2)
Requires-Dist: pyjwt (==2.6.0)
Requires-Dist: python-dateutil (==2.8.2)
Requires-Dist: pytz (==2022.6)
Requires-Dist: redis (==3.0.0)
Requires-Dist: requests (==2.28.1)
Requires-Dist: rq (==1.0)
Requires-Dist: setuptools (==65.5.1)
Requires-Dist: sgmllib3k (==1.0.0)
Requires-Dist: six (==1.16.0)
Requires-Dist: soupsieve (==2.3.2.post1)
Requires-Dist: tempora (==5.0.2)
Requires-Dist: typing-extensions (==4.4.0)
Requires-Dist: urllib3 (==1.26.12)
Requires-Dist: zc-lockfile (==2.0)
Project-URL: Bug Tracker, https://github.com/chaoss/grimoirelab-kingarthur/issues
Project-URL: Repository, https://github.com/chaoss/grimoirelab-kingarthur
